deepdow/__init__.py
deepdow/benchmarks.py
deepdow/callbacks.py
deepdow/experiments.py
deepdow/explain.py
deepdow/losses.py
deepdow/nn.py
deepdow/utils.py
deepdow/visualize.py
deepdow/data/__init__.py
deepdow/data/augment.py
deepdow/data/load.py
deepdow/data/synthetic.py
deepdow/layers/__init__.py
deepdow/layers/allocate.py
deepdow/layers/collapse.py
deepdow/layers/misc.py
deepdow/layers/transform.py
deepdow-0.2.3.dist-info/LICENSE
deepdow-0.2.3.dist-info/METADATA
deepdow-0.2.3.dist-info/WHEEL
deepdow-0.2.3.dist-info/top_level.txt
deepdow-0.2.3.dist-info/RECORD
