Metadata-Version: 2.1
Name: deepdow
Version: 0.2.3
Summary: Portfolio optimization with deep learning
Home-page: https://github.com/jankrepl/deepdow
Author: Jan Krepl
Author-email: kjan.official@gmail.com
License: Apache License 2.0
Requires-Python: >=3.6
License-File: LICENSE
Requires-Dist: cvxpylayers
Requires-Dist: matplotlib
Requires-Dist: mlflow
Requires-Dist: numpy >=1.16.5
Requires-Dist: pandas
Requires-Dist: pillow
Requires-Dist: seaborn
Requires-Dist: torch >=1.5
Requires-Dist: tensorboard
Requires-Dist: tqdm
Provides-Extra: dev
Requires-Dist: codecov ; extra == 'dev'
Requires-Dist: flake8 ==3.7.9 ; extra == 'dev'
Requires-Dist: pydocstyle ; extra == 'dev'
Requires-Dist: pytest >=4.6 ; extra == 'dev'
Requires-Dist: pytest-cov ; extra == 'dev'
Requires-Dist: tox ; extra == 'dev'
Provides-Extra: docs
Requires-Dist: sphinx ; extra == 'docs'
Requires-Dist: sphinx-rtd-theme ; extra == 'docs'
Provides-Extra: examples
Requires-Dist: sphinx-gallery ; extra == 'examples'
Requires-Dist: statsmodels ; extra == 'examples'
